MANIFEST.in
README.rst
setup.py
GeoFormAlchemy.egg-info/PKG-INFO
GeoFormAlchemy.egg-info/SOURCES.txt
GeoFormAlchemy.egg-info/dependency_links.txt
GeoFormAlchemy.egg-info/entry_points.txt
GeoFormAlchemy.egg-info/requires.txt
GeoFormAlchemy.egg-info/top_level.txt
GeoFormAlchemy.egg-info/zip-safe
geoformalchemy/__init__.py
geoformalchemy/base.py
geoformalchemy/pylons/__init__.py
geoformalchemy/pylons/paster_template.py
geoformalchemy/pylons/project/+package+/public/adminapp/images/remove_feature_off.png
geoformalchemy/pylons/project/+package+/public/adminapp/images/remove_feature_on.png
geoformalchemy/pylons/project/+package+/public/adminapp/images/select_feature_off.png
geoformalchemy/pylons/project/+package+/public/adminapp/images/select_feature_on.png
geoformalchemy/pylons/project/+package+/templates/forms/map.mako
geoformalchemy/pylons/project/+package+/templates/forms/map_js.mako
geoformalchemy/pylons/project/+package+/templates/forms/run.mako