Metadata-Version: 1.0
Name: GeoFormAlchemy
Version: 0.4
Summary: GeoFormAlchemy - a extension for FormAlchemy that adds support for spatial databases
Home-page: http://github.com/camptocamp/GeoFormAlchemy
Author: Camptocamp
Author-email: UNKNOWN
License: MIT
Keywords: gis sqlalchemy geoalchemy formalchemy
Platform: UNKNOWN
Classifier: Development Status :: 3 - Alpha
Classifier: Intended Audience :: Developers
Classifier: License :: OSI Approved :: MIT License
Classifier: Operating System :: OS Independent
Classifier: Programming Language :: Python
Classifier: Framework :: Pylons
Classifier: Topic :: Internet :: WWW/HTTP
Classifier: Topic :: Internet :: WWW/HTTP :: Dynamic Content
Classifier: Topic :: Software Development :: Libraries :: Python Modules
Classifier: Topic :: Software Development :: User Interfaces
Classifier: Topic :: Text Processing :: Markup :: HTML
